thumbor_carousel-0.2.0.dist-info/METADATA
thumbor_carousel-0.2.0.dist-info/WHEEL
thumbor_carousel/__init__.py
thumbor_carousel-0.2.0.dist-info/RECORD
